LICENSE
MANIFEST.in
setup.py
gmaps_places/__init__.py
gmaps_places/admin.py
gmaps_places/conf.py
gmaps_places/forms.py
gmaps_places/models.py
gmaps_places/tests.py
gmaps_places/utils.py
gmaps_places/static/gmaps_places/.gmaps_places.js.un~
gmaps_places/static/gmaps_places/.gmaps_places_form.js.un~
gmaps_places/static/gmaps_places/.gmaps_places_old.js.un~
gmaps_places/static/gmaps_places/TO_DELETE_gmaps_places_form.js
gmaps_places/static/gmaps_places/TO_DELETE_gmaps_places_old.js
gmaps_places/static/gmaps_places/gmaps_places.js
gmaps_places/static/gmaps_places/flags/blank.png
gmaps_places/static/gmaps_places/flags/flags.css
gmaps_places/static/gmaps_places/flags/flags.png
twentytab_gmaps_places.egg-info/PKG-INFO
twentytab_gmaps_places.egg-info/SOURCES.txt
twentytab_gmaps_places.egg-info/dependency_links.txt
twentytab_gmaps_places.egg-info/requires.txt
twentytab_gmaps_places.egg-info/top_level.txt