Metadata-Version: 1.0
Name: twentytab-gmaps-places
Version: 0.17
Summary: A django app on top of twentytab-gmapsmarkers and google maps api v3 to manage geolocation and markers with all the administrative level details
Home-page: https://github.com/20tab/twentytab-gmaps-places
Author: 20tab S.r.l.
Author-email: info@20tab.com
License: MIT License
Platform: UNKNOWN
